{
  "image": "/home/michael/soma/Bthesis_Dataset/03_sub_cell/C029_A043_sub.png",
  "lines_json": "/Users/niihosoushin/Desktop/BlackMask/05_raf_image_json/C029_A043_raf.json",
  "bbox_json": "/Users/niihosoushin/Desktop/BlackMask/10_output_groundingdino_swiml_prompt_v1/C029_A043_sub.json",
  "criteria": {
    "min_pixels": 10,
    "min_ratio": 0.0005,
    "judge_thresh": 0.02
  },
  "selected_labels": [
    "eyes",
    "eyes",
    "face",
    "nose",
    "arm",
    "person",
    "mouth",
    "leg",
    "head",
    "arm",
    "head"
  ],
  "selected_detections": [
    {
      "det_index": 4,
      "label": "eyes",
      "score": 0.5521975755691528,
      "bbox_xyxy": [
        863.1287231445312,
        209.6562042236328,
        884.39453125,
        229.1729278564453
      ],
      "bbox_xyxy_int_inclusive": [
        863,
        209,
        884,
        229
      ],
      "ink_pixels": 339,
      "bbox_area": 462,
      "ink_ratio": 0.7337662337662337,
      "has_ink": true,
      "judge_score": 0.4051839353202225
    },
    {
      "det_index": 5,
      "label": "eyes",
      "score": 0.5399028658866882,
      "bbox_xyxy": [
        835.98828125,
        217.91831970214844,
        853.2828369140625,
        238.39891052246094
      ],
      "bbox_xyxy_int_inclusive": [
        835,
        217,
        853,
        238
      ],
      "ink_pixels": 303,
      "bbox_area": 418,
      "ink_ratio": 0.7248803827751196,
      "has_ink": true,
      "judge_score": 0.3913649960853266
    },
    {
      "det_index": 1,
      "label": "face",
      "score": 0.6712959408760071,
      "bbox_xyxy": [
        830.5228881835938,
        202.56869506835938,
        900.6076049804688,
        271.57720947265625
      ],
      "bbox_xyxy_int_inclusive": [
        830,
        202,
        900,
        271
      ],
      "ink_pixels": 2339,
      "bbox_area": 4970,
      "ink_ratio": 0.4706237424547284,
      "has_ink": true,
      "judge_score": 0.3159278079897345
    },
    {
      "det_index": 0,
      "label": "nose",
      "score": 0.6998879909515381,
      "bbox_xyxy": [
        849.0911254882812,
        228.59603881835938,
        868.1319580078125,
        252.24374389648438
      ],
      "bbox_xyxy_int_inclusive": [
        849,
        228,
        868,
        252
      ],
      "ink_pixels": 211,
      "bbox_area": 500,
      "ink_ratio": 0.422,
      "has_ink": true,
      "judge_score": 0.29535273218154906
    },
    {
      "det_index": 7,
      "label": "arm",
      "score": 0.3717334270477295,
      "bbox_xyxy": [
        761.3654174804688,
        278.0799255371094,
        896.2196655273438,
        344.37896728515625
      ],
      "bbox_xyxy_int_inclusive": [
        761,
        278,
        896,
        344
      ],
      "ink_pixels": 4286,
      "bbox_area": 9112,
      "ink_ratio": 0.4703687445127305,
      "has_ink": true,
      "judge_score": 0.1748517853738552
    },
    {
      "det_index": 2,
      "label": "person",
      "score": 0.6409316062927246,
      "bbox_xyxy": [
        687.6666870117188,
        117.23993682861328,
        1025.009765625,
        682.2015991210938
      ],
      "bbox_xyxy_int_inclusive": [
        687,
        117,
        1025,
        682
      ],
      "ink_pixels": 43068,
      "bbox_area": 191874,
      "ink_ratio": 0.22445980174489508,
      "has_ink": true,
      "judge_score": 0.1438633812805021
    },
    {
      "det_index": 3,
      "label": "mouth",
      "score": 0.624445378780365,
      "bbox_xyxy": [
        848.5823974609375,
        241.12733459472656,
        867.7465209960938,
        254.29832458496094
      ],
      "bbox_xyxy_int_inclusive": [
        848,
        241,
        867,
        254
      ],
      "ink_pixels": 63,
      "bbox_area": 280,
      "ink_ratio": 0.225,
      "has_ink": true,
      "judge_score": 0.14050021022558212
    },
    {
      "det_index": 6,
      "label": "leg",
      "score": 0.3898771405220032,
      "bbox_xyxy": [
        842.3667602539062,
        468.7744445800781,
        986.7376098632812,
        676.37744140625
      ],
      "bbox_xyxy_int_inclusive": [
        842,
        468,
        986,
        676
      ],
      "ink_pixels": 10022,
      "bbox_area": 30305,
      "ink_ratio": 0.3307045042072265,
      "has_ink": true,
      "judge_score": 0.12893412645806024
    },
    {
      "det_index": 9,
      "label": "head",
      "score": 0.31066155433654785,
      "bbox_xyxy": [
        805.3243408203125,
        174.37843322753906,
        937.0831298828125,
        279.4444274902344
      ],
      "bbox_xyxy_int_inclusive": [
        805,
        174,
        937,
        279
      ],
      "ink_pixels": 5434,
      "bbox_area": 14098,
      "ink_ratio": 0.38544474393531,
      "has_ink": true,
      "judge_score": 0.11974286326179608
    },
    {
      "det_index": 10,
      "label": "arm",
      "score": 0.30237558484077454,
      "bbox_xyxy": [
        864.2254638671875,
        249.6623077392578,
        962.2811889648438,
        323.7649841308594
      ],
      "bbox_xyxy_int_inclusive": [
        864,
        249,
        962,
        323
      ],
      "ink_pixels": 2482,
      "bbox_area": 7425,
      "ink_ratio": 0.3342760942760943,
      "has_ink": true,
      "judge_score": 0.1010769295050239
    },
    {
      "det_index": 8,
      "label": "head",
      "score": 0.3507886528968811,
      "bbox_xyxy": [
        795.3919067382812,
        116.48578643798828,
        948.2953491210938,
        277.8955383300781
      ],
      "bbox_xyxy_int_inclusive": [
        795,
        116,
        948,
        277
      ],
      "ink_pixels": 6669,
      "bbox_area": 24948,
      "ink_ratio": 0.26731601731601734,
      "has_ink": true,
      "judge_score": 0.09377142561204506
    }
  ],
  "all_scored_detections": [
    {
      "det_index": 4,
      "label": "eyes",
      "score": 0.5521975755691528,
      "bbox_xyxy": [
        863.1287231445312,
        209.6562042236328,
        884.39453125,
        229.1729278564453
      ],
      "bbox_xyxy_int_inclusive": [
        863,
        209,
        884,
        229
      ],
      "ink_pixels": 339,
      "bbox_area": 462,
      "ink_ratio": 0.7337662337662337,
      "has_ink": true,
      "judge_score": 0.4051839353202225
    },
    {
      "det_index": 5,
      "label": "eyes",
      "score": 0.5399028658866882,
      "bbox_xyxy": [
        835.98828125,
        217.91831970214844,
        853.2828369140625,
        238.39891052246094
      ],
      "bbox_xyxy_int_inclusive": [
        835,
        217,
        853,
        238
      ],
      "ink_pixels": 303,
      "bbox_area": 418,
      "ink_ratio": 0.7248803827751196,
      "has_ink": true,
      "judge_score": 0.3913649960853266
    },
    {
      "det_index": 1,
      "label": "face",
      "score": 0.6712959408760071,
      "bbox_xyxy": [
        830.5228881835938,
        202.56869506835938,
        900.6076049804688,
        271.57720947265625
      ],
      "bbox_xyxy_int_inclusive": [
        830,
        202,
        900,
        271
      ],
      "ink_pixels": 2339,
      "bbox_area": 4970,
      "ink_ratio": 0.4706237424547284,
      "has_ink": true,
      "judge_score": 0.3159278079897345
    },
    {
      "det_index": 0,
      "label": "nose",
      "score": 0.6998879909515381,
      "bbox_xyxy": [
        849.0911254882812,
        228.59603881835938,
        868.1319580078125,
        252.24374389648438
      ],
      "bbox_xyxy_int_inclusive": [
        849,
        228,
        868,
        252
      ],
      "ink_pixels": 211,
      "bbox_area": 500,
      "ink_ratio": 0.422,
      "has_ink": true,
      "judge_score": 0.29535273218154906
    },
    {
      "det_index": 7,
      "label": "arm",
      "score": 0.3717334270477295,
      "bbox_xyxy": [
        761.3654174804688,
        278.0799255371094,
        896.2196655273438,
        344.37896728515625
      ],
      "bbox_xyxy_int_inclusive": [
        761,
        278,
        896,
        344
      ],
      "ink_pixels": 4286,
      "bbox_area": 9112,
      "ink_ratio": 0.4703687445127305,
      "has_ink": true,
      "judge_score": 0.1748517853738552
    },
    {
      "det_index": 2,
      "label": "person",
      "score": 0.6409316062927246,
      "bbox_xyxy": [
        687.6666870117188,
        117.23993682861328,
        1025.009765625,
        682.2015991210938
      ],
      "bbox_xyxy_int_inclusive": [
        687,
        117,
        1025,
        682
      ],
      "ink_pixels": 43068,
      "bbox_area": 191874,
      "ink_ratio": 0.22445980174489508,
      "has_ink": true,
      "judge_score": 0.1438633812805021
    },
    {
      "det_index": 3,
      "label": "mouth",
      "score": 0.624445378780365,
      "bbox_xyxy": [
        848.5823974609375,
        241.12733459472656,
        867.7465209960938,
        254.29832458496094
      ],
      "bbox_xyxy_int_inclusive": [
        848,
        241,
        867,
        254
      ],
      "ink_pixels": 63,
      "bbox_area": 280,
      "ink_ratio": 0.225,
      "has_ink": true,
      "judge_score": 0.14050021022558212
    },
    {
      "det_index": 6,
      "label": "leg",
      "score": 0.3898771405220032,
      "bbox_xyxy": [
        842.3667602539062,
        468.7744445800781,
        986.7376098632812,
        676.37744140625
      ],
      "bbox_xyxy_int_inclusive": [
        842,
        468,
        986,
        676
      ],
      "ink_pixels": 10022,
      "bbox_area": 30305,
      "ink_ratio": 0.3307045042072265,
      "has_ink": true,
      "judge_score": 0.12893412645806024
    },
    {
      "det_index": 9,
      "label": "head",
      "score": 0.31066155433654785,
      "bbox_xyxy": [
        805.3243408203125,
        174.37843322753906,
        937.0831298828125,
        279.4444274902344
      ],
      "bbox_xyxy_int_inclusive": [
        805,
        174,
        937,
        279
      ],
      "ink_pixels": 5434,
      "bbox_area": 14098,
      "ink_ratio": 0.38544474393531,
      "has_ink": true,
      "judge_score": 0.11974286326179608
    },
    {
      "det_index": 10,
      "label": "arm",
      "score": 0.30237558484077454,
      "bbox_xyxy": [
        864.2254638671875,
        249.6623077392578,
        962.2811889648438,
        323.7649841308594
      ],
      "bbox_xyxy_int_inclusive": [
        864,
        249,
        962,
        323
      ],
      "ink_pixels": 2482,
      "bbox_area": 7425,
      "ink_ratio": 0.3342760942760943,
      "has_ink": true,
      "judge_score": 0.1010769295050239
    },
    {
      "det_index": 8,
      "label": "head",
      "score": 0.3507886528968811,
      "bbox_xyxy": [
        795.3919067382812,
        116.48578643798828,
        948.2953491210938,
        277.8955383300781
      ],
      "bbox_xyxy_int_inclusive": [
        795,
        116,
        948,
        277
      ],
      "ink_pixels": 6669,
      "bbox_area": 24948,
      "ink_ratio": 0.26731601731601734,
      "has_ink": true,
      "judge_score": 0.09377142561204506
    }
  ]
}