{
  "image": "/home/michael/soma/Bthesis_Dataset/03_sub_cell/C037_A001_sub.png",
  "text_prompt": "face . eyes . mouth . arm . head . leg . nose . person .",
  "entities": [
    "face",
    "eyes",
    "mouth",
    "arm",
    "head",
    "leg",
    "nose",
    "person"
  ],
  "pred_score_thr": 0.3,
  "detections": [
    {
      "label": "person",
      "score": 0.563350260257721,
      "bbox_xyxy": [
        182.22572326660156,
        0.0,
        1840.5487060546875,
        1049.10595703125
      ]
    },
    {
      "label": "head",
      "score": 0.5461183786392212,
      "bbox_xyxy": [
        183.44891357421875,
        1.1379057168960571,
        1837.533447265625,
        1047.9923095703125
      ]
    },
    {
      "label": "eyes",
      "score": 0.42648008465766907,
      "bbox_xyxy": [
        465.34417724609375,
        160.78746032714844,
        1673.3365478515625,
        1046.82666015625
      ]
    },
    {
      "label": "face",
      "score": 0.41681891679763794,
      "bbox_xyxy": [
        183.44891357421875,
        1.1379057168960571,
        1837.533447265625,
        1047.9923095703125
      ]
    },
    {
      "label": "nose",
      "score": 0.3315402567386627,
      "bbox_xyxy": [
        457.3478088378906,
        576.6677856445312,
        794.8777465820312,
        1047.5225830078125
      ]
    }
  ]
}