{
  "image": "/home/michael/soma/Bthesis_Dataset/03_sub_cell/C092_A017_sub.png",
  "text_prompt": "face . eyes . mouth . arm . head . leg . nose . person . ears . clothes . eyebrows .",
  "entities": [
    "face",
    "eyes",
    "mouth",
    "arm",
    "head",
    "leg",
    "nose",
    "person",
    "ears",
    "clothes",
    "eyebrows"
  ],
  "pred_score_thr": 0.3,
  "detections": [
    {
      "label": "leg",
      "score": 0.4301086664199829,
      "bbox_xyxy": [
        1022.8998413085938,
        500.490234375,
        1062.0577392578125,
        543.1289672851562
      ]
    },
    {
      "label": "person",
      "score": 0.4121914803981781,
      "bbox_xyxy": [
        929.651123046875,
        384.284912109375,
        1137.31494140625,
        560.5215454101562
      ]
    },
    {
      "label": "person",
      "score": 0.365404337644577,
      "bbox_xyxy": [
        1010.7369995117188,
        402.8006591796875,
        1100.31689453125,
        559.7298583984375
      ]
    },
    {
      "label": "head",
      "score": 0.3587311804294586,
      "bbox_xyxy": [
        1040.528076171875,
        402.6767272949219,
        1073.700927734375,
        420.60186767578125
      ]
    },
    {
      "label": "clothes",
      "score": 0.34335967898368835,
      "bbox_xyxy": [
        1038.2081298828125,
        414.518798828125,
        1069.9512939453125,
        463.594482421875
      ]
    },
    {
      "label": "clothes",
      "score": 0.3407289981842041,
      "bbox_xyxy": [
        1047.2044677734375,
        450.7645263671875,
        1093.502197265625,
        517.3212890625
      ]
    },
    {
      "label": "leg",
      "score": 0.33998265862464905,
      "bbox_xyxy": [
        1076.9097900390625,
        489.0740966796875,
        1101.060302734375,
        549.8590698242188
      ]
    },
    {
      "label": "leg",
      "score": 0.32069507241249084,
      "bbox_xyxy": [
        1013.0114135742188,
        500.573974609375,
        1061.9998779296875,
        559.3645629882812
      ]
    },
    {
      "label": "person",
      "score": 0.3125764727592468,
      "bbox_xyxy": [
        1010.0751342773438,
        402.9978942871094,
        1137.0828857421875,
        560.0250854492188
      ]
    },
    {
      "label": "ears",
      "score": 0.3069508969783783,
      "bbox_xyxy": [
        1061.5924072265625,
        404.9988708496094,
        1073.853515625,
        417.40802001953125
      ]
    }
  ]
}